AUTHORS.rst
CONTRIBUTING.rst
HISTORY.rst
LICENSE
MANIFEST.in
README.rst
setup.cfg
setup.py
dj_geocoding/__init__.py
dj_geocoding/admin.py
dj_geocoding/models.py
dj_geocoding/utils.py
dj_geocoding.egg-info/PKG-INFO
dj_geocoding.egg-info/SOURCES.txt
dj_geocoding.egg-info/dependency_links.txt
dj_geocoding.egg-info/not-zip-safe
dj_geocoding.egg-info/requires.txt
dj_geocoding.egg-info/top_level.txt