Metadata-Version: 1.1
Name: dj-geocoding
Version: 0.1.0
Summary: Django integration for geocoding (using Geocodio)
Home-page: https://github.com/bennylope/dj-geocoding
Author: Ben Lopatin
Author-email: ben@wellfire.co
License: BSD
Keywords: dj-geocoding
Platform: UNKNOWN
Classifier: Development Status :: 3 - Alpha
Classifier: Framework :: Django
Classifier: Intended Audience :: Developers
Classifier: License :: OSI Approved :: BSD License
Classifier: Natural Language :: English
Classifier: Programming Language :: Python :: 2
Classifier: Programming Language :: Python :: 2.6
Classifier: Programming Language :: Python :: 2.7
Classifier: Programming Language :: Python :: 3
Classifier: Programming Language :: Python :: 3.3
